{
    "userName" : "hh",

    "cloudServer": {
        "host": "39.97.106.35",
        "port" : 22,
        "username": "root",
        "pwd": "Wojiaomt1",
        "reverse_port": 9870
    },

    "marketServer": {
        "host": "localhost"
    },

    "tradeServer": {
        "host": "172.29.45.160",
        "port" : 22,
        "username": "root",
        "pwd": "CYQH@tg160"
    },

    "localUIDir": "D:\\local_repo\\CTA_UI",
    
    "accountList": ["cy"],

    "tradeDirList": ["/root/cta_cy_co1"]
}
